<?xml version="1.0"?>
<FSData version="9.0">
	<Airport displayName="Nationaal Zweefvlieg Centrum Terlet" groupID="1" groupGenerated="FALSE" country="Netherlands" city="Terlet" name="Nationaal Zweefvlieg Centrum Terlet" ident="EHTL" lat="52.05436111000000" lon="5.91639722000000" alt="0.00000000000000" magvar="0.000000" airportTestRadius="2000.00000000000000" applyFlatten="FALSE" isOnTIN="FALSE">
		<Runway displayName="14R-32L" parentGroupID="1" lat="52.04973030019303" lon="5.92431771262492" alt="63.31263438519090" heading="132.00001525878906" length="1500.00000000000000" width="25.80000686645508" patternAltitude="304.79998779296875" surface="{43E7E61A-16BF-49B5-AA3F-BE7AD969B1FC}" transparent="FALSE" number="13" designator="NONE" primaryLanding="TRUE" primaryTakeoff="TRUE" primaryPattern="RIGHT" secondaryLanding="TRUE" secondaryTakeoff="TRUE" secondaryPattern="LEFT" primaryMarkingBias="0.00000000000000" secondaryMarkingBias="0.00000000000000" groundMerging="TRUE" excludeVegetationAround="TRUE">
			<Markings edges="FALSE" threshold="FALSE" alternateThreshold="FALSE" fixedDistance="FALSE" alternateFixedDistance="FALSE" touchdown="FALSE" alternateTouchdown="FALSE" dashes="FALSE" ident="FALSE" leadingZeroIdent="FALSE" precision="FALSE" alternatePrecision="FALSE" edgePavement="FALSE" singleEnd="FALSE" primaryClosed="FALSE" secondaryClosed="FALSE" primaryStol="FALSE" secondaryStol="FALSE" noThresholdEndArrows="FALSE"/>
			<Lights center="NONE" edge="NONE"/>
			<RunwayStart end="PRIMARY" lat="52.05390289477743" lon="5.91682626726794" alt="62.96531107462943" heading="135.00001525878906"/>
			<RunwayStart end="SECONDARY" lat="52.04553851706935" lon="5.93183845070288" alt="63.73493450693786" heading="315.00067138671875"/>
		</Runway>
		<Aprons/>
		<PaintedElements/>
		<ApronEdgeLights/>
		<Com frequency="100.000000" type="UNICOM" name="130.130"/>
	</Airport>
</FSData>

